odoo/addons/partner_account_multicompany_default/README.rst
odoo/addons/partner_account_multicompany_default/__init__.py
odoo/addons/partner_account_multicompany_default/__manifest__.py
odoo/addons/partner_account_multicompany_default/i18n/it.po
odoo/addons/partner_account_multicompany_default/i18n/partner_account_multicompany_default.pot
odoo/addons/partner_account_multicompany_default/models/__init__.py
odoo/addons/partner_account_multicompany_default/models/partner.py
odoo/addons/partner_account_multicompany_default/readme/CONFIGURE.rst
odoo/addons/partner_account_multicompany_default/readme/CONTRIBUTORS.rst
odoo/addons/partner_account_multicompany_default/readme/DESCRIPTION.rst
odoo/addons/partner_account_multicompany_default/readme/ROADMAP.rst
odoo/addons/partner_account_multicompany_default/readme/USAGE.rst
odoo/addons/partner_account_multicompany_default/static/description/icon.png
odoo/addons/partner_account_multicompany_default/static/description/index.html
odoo/addons/partner_account_multicompany_default/tests/__init__.py
odoo/addons/partner_account_multicompany_default/tests/test_partner.py
odoo/addons/partner_account_multicompany_default/views/partner_view.xml
odoo_addon_partner_account_multicompany_default-16.0.0.1.0.3.dist-info/METADATA
odoo_addon_partner_account_multicompany_default-16.0.0.1.0.3.dist-info/WHEEL
odoo_addon_partner_account_multicompany_default-16.0.0.1.0.3.dist-info/top_level.txt
odoo_addon_partner_account_multicompany_default-16.0.0.1.0.3.dist-info/RECORD
